tobii_pytracker/__init__.py
tobii_pytracker/main.py
tobii_pytracker/configs/__init__.py
tobii_pytracker/configs/custom_config.py
tobii_pytracker/datasets/__init__.py
tobii_pytracker/datasets/custom_dataset.py
tobii_pytracker/models/__init__.py
tobii_pytracker/models/custom_model.py
tobii_pytracker/models/custom_yolo_model.py
tobii_pytracker/utils/__init__.py
tobii_pytracker/utils/custom_logger.py
tobii_pytracker/utils/eyetracker.py
tobii_pytracker/utils/gui.py
tobii_pytracker/utils/voice.py
tobii_pytracker-0.1.0.dist-info/METADATA
tobii_pytracker-0.1.0.dist-info/WHEEL
tobii_pytracker-0.1.0.dist-info/entry_points.txt
tobii_pytracker-0.1.0.dist-info/top_level.txt
tobii_pytracker-0.1.0.dist-info/RECORD
