Metadata-Version: 2.4
Name: tobii-pytracker
Version: 0.1.0
Summary: A Python-based framework for Tobii eye tracker experiments and multimodal interaction.
Home-page: https://github.com/sbobek/tobii-pytracker
Author: Szymon Bobek
Author-email: Szymon Bobek <szymon.bobek@gmail.com>
License: MIT
Classifier: Programming Language :: Python :: 3
Classifier: License :: OSI Approved :: MIT License
Classifier: Operating System :: OS Independent
Classifier: Topic :: Scientific/Engineering :: Human Machine Interfaces
Requires-Python: <3.11,>=3.10
Requires-Dist: six==1.16.0
Requires-Dist: packaging==24.0
Requires-Dist: numpy==1.26.4
Requires-Dist: PyYAML==6.0.1
Requires-Dist: pyserial==3.5
Requires-Dist: scipy==1.13.1
Requires-Dist: json_tricks==3.17.3
Requires-Dist: requests==2.32.2
Requires-Dist: pyglet==1.5.2
Requires-Dist: Pillow==10.3.0
Requires-Dist: python-bidi==0.4.2
Requires-Dist: pandas==2.2.2
Requires-Dist: arabic_reshaper==3.0.0
Requires-Dist: freetype-py==2.4.0
Requires-Dist: matplotlib==3.9.0
Requires-Dist: psutil==5.9.8
Requires-Dist: gevent==24.2.1
Requires-Dist: msgpack==1.0.8
Requires-Dist: pywin32==311; platform_system == "Windows"
Requires-Dist: sounddevice==0.5.3; platform_system == "Windows"
Requires-Dist: soundfile==0.13.1; platform_system == "Windows"
